etabackend/__init__.py
etabackend/__main__.py
etabackend/backend.py
etabackend/clip.py
etabackend/eta.py
etabackend/eta_script.py
etabackend/recipe.py
etabackend/task.py
etabackend/util.py
etabackend/etalang/__init__.py
etabackend/etalang/ast_parser.py
etabackend/etalang/eta_exp.py
etabackend/etalang/eta_parser.py
etabackend/etalang/eta_vm.py
etabackend/etalang/graph_parser.py
etabackend/etalang/jit_linker.py
etabackend/etalang/recipe_compiler.py
etabackend/etalang/tensor.py
etabackend/ll/m1/.gitkeep
etabackend/ll/m1/INFRA_vchn.ll
etabackend/ll/m1/PARSE_TimeTagFileHeader.ll
etabackend/ll/m1/PARSE_TimeTags.ll
etabackend/ll/nt/INFRA_vchn.ll
etabackend/ll/nt/PARSE_TimeTagFileHeader.ll
etabackend/ll/nt/PARSE_TimeTags.ll
etabackend/ll/posix/.gitkeep
etabackend/ll/posix/INFRA_vchn.ll
etabackend/ll/posix/PARSE_TimeTagFileHeader.ll
etabackend/ll/posix/PARSE_TimeTags.ll
etabackend/static/design.html
etabackend/static/eta.png
etabackend/static/favicon.ico
etabackend/static/help.html
etabackend/static/index.html
etabackend/static/processing.html
etabackend/static/css/bootstrap.min.css
etabackend/static/css/code.css
etabackend/static/css/design.css
etabackend/static/css/frame.css
etabackend/static/css/index.css
etabackend/static/css/layout.css
etabackend/static/css/processing.css
etabackend/static/css/table.css
etabackend/static/css/fontawesome/css/fa-brands.css
etabackend/static/css/fontawesome/css/fa-brands.min.css
etabackend/static/css/fontawesome/css/fa-regular.css
etabackend/static/css/fontawesome/css/fa-regular.min.css
etabackend/static/css/fontawesome/css/fa-solid.css
etabackend/static/css/fontawesome/css/fa-solid.min.css
etabackend/static/css/fontawesome/css/fontawesome-all.css
etabackend/static/css/fontawesome/css/fontawesome-all.min.css
etabackend/static/css/fontawesome/css/fontawesome.css
etabackend/static/css/fontawesome/css/fontawesome.min.css
etabackend/static/css/fontawesome/webfonts/fa-brands-400.eot
etabackend/static/css/fontawesome/webfonts/fa-brands-400.svg
etabackend-0.9.9.dist-info/LICENSE
etabackend-0.9.9.dist-info/METADATA
etabackend-0.9.9.dist-info/WHEEL
etabackend-0.9.9.dist-info/top_level.txt
etabackend-0.9.9.dist-info/RECORD
